{
  "project_info": {
    "project_number": "61962162157",
    "firebase_url": "https://categories-database-85469.firebaseio.com",
    "project_id": "categories-database-85469",
    "storage_bucket": "categories-database-85469.appspot.com"
  },
  "client": [
    {
      "client_info": {
        "mobilesdk_app_id": "1:61962162157:android:37b6f272cea7af27fb21e4",
        "android_client_info": {
          "package_name": "com.example.project.communityprojectapptest"
        }
      },
      "oauth_client": [
        {
          "client_id": "61962162157-4ktd2h73r2moeorad5geqgu8fr2a370c.apps.googleusercontent.com",
          "client_type": 1,
          "android_info": {
            "package_name": "com.example.project.communityprojectapptest",
            "certificate_hash": "8632a619fae6d80204cd77eadd586d82fbbf5127"
          }
        },
        {
          "client_id": "61962162157-sjvt28i32eidog7odtcgub746krgvi0d.apps.googleusercontent.com",
          "client_type": 3
        }
      ],
      "api_key": [
        {
          "current_key": "AIzaSyCMl10ztRNL33xqJfu1IKvKTBD2Rfic2Pc"
        },
        {
          "current_key": "AIzaSyCOOV5cTf7k1TXcwsvotfTvmzJKaVsx5Uo"
        }
      ],
      "services": {
        "appinvite_service": {
          "other_platform_oauth_client": [
            {
              "client_id": "61962162157-sjvt28i32eidog7odtcgub746krgvi0d.apps.googleusercontent.com",
              "client_type": 3
            }
          ]
        }
      }
    },
    {
      "client_info": {
        "mobilesdk_app_id": "1:61962162157:android:e9e87b13b772aae5fb21e4",
        "android_client_info": {
          "package_name": "com.example.project.waste_recognition_app"
        }
      },
      "oauth_client": [
        {
          "client_id": "61962162157-6k0g7o2mk8ulic225a4vhn9qjqijuqt7.apps.googleusercontent.com",
          "client_type": 1,
          "android_info": {
            "package_name": "com.example.project.waste_recognition_app",
            "certificate_hash": "d8a8c00d1d945696253d09230f303abe00c87840"
          }
        },
        {
          "client_id": "61962162157-sjvt28i32eidog7odtcgub746krgvi0d.apps.googleusercontent.com",
          "client_type": 3
        }
      ],
      "api_key": [
        {
          "current_key": "AIzaSyCMl10ztRNL33xqJfu1IKvKTBD2Rfic2Pc"
        },
        {
          "current_key": "AIzaSyCOOV5cTf7k1TXcwsvotfTvmzJKaVsx5Uo"
        }
      ],
      "services": {
        "appinvite_service": {
          "other_platform_oauth_client": [
            {
              "client_id": "61962162157-sjvt28i32eidog7odtcgub746krgvi0d.apps.googleusercontent.com",
              "client_type": 3
            }
          ]
        }
      }
    }
  ],
  "configuration_version": "1"
}